{
    "configurations": [
        {
            "name": "arm_cortex_m",
            "includePath": [
                "${workspaceFolder}/**"
            ],
            "defines": [
                "USE_HAL_DRIVER",
                "STM32F469xx"
            ],
            "windowsSdkVersion": "10.0.18362.0",
            "compilerPath": "C:\\Program Files (x86)\\GNU Arm Embedded Toolchain\\10 2021.10\\bin\\arm-none-eabi-gcc.exe",
            "cStandard": "c11",
            "cppStandard": "c++11",
            "intelliSenseMode": "windows-gcc-arm"
        }
    ],
    "version": 4
}